README.rst
setup.py
clitool/__init__.py
clitool/_unicodecsv.py
clitool/accesslog.py
clitool/cli.py
clitool/config.py
clitool/processor.py
clitool/textio.py
clitool/urlutils.py
clitool.egg-info/PKG-INFO
clitool.egg-info/SOURCES.txt
clitool.egg-info/dependency_links.txt
clitool.egg-info/entry_points.txt
clitool.egg-info/not-zip-safe
clitool.egg-info/requires.txt
clitool.egg-info/top_level.txt