Metadata-Version: 1.0
Name: clitool
Version: 0.4.0
Summary: Command Line Tool Utilities
Home-page: https://github.com/skitazaki/python-clitool
Author: KITAZAKI Shigeru
Author-email: skitazaki@gmail.com
License: Apache
Platform: UNKNOWN
Classifier: Development Status :: 4 - Beta
Classifier: Environment :: Console
Classifier: Intended Audience :: Developers
Classifier: Intended Audience :: Education
